form_utils/__init__.py
form_utils/custom_qwidgets.py
form_utils/datatypes.py
form_utils/form.py
form_utils/forms.py
qss_utils/__init__.py
qss_utils/style.py
pyqt6_utils-0.5.0.dist-info/LICENSE
pyqt6_utils-0.5.0.dist-info/METADATA
pyqt6_utils-0.5.0.dist-info/WHEEL
pyqt6_utils-0.5.0.dist-info/top_level.txt
pyqt6_utils-0.5.0.dist-info/RECORD
