Metadata-Version: 2.1
Name: pyqt6-utils
Version: 0.5.0
Summary: Utils for PyQt6 (In past: pyqt6-forms)
Home-page: https://github.com/gloger2003/pyqt6-forms
Author: gloger2003 (Anight Studio)
Author-email: excelsior7554@gmail.com
License: UNKNOWN
Platform: UNKNOWN
Classifier: Programming Language :: Python :: 3.10
Classifier: License :: OSI Approved :: Apache Software License
Classifier: Operating System :: OS Independent
Requires-Python: >=3.10
License-File: LICENSE
